nameflux/__init__.py
nameflux/__main__.py
nameflux-2.1.2.dist-info/LICENSE
nameflux-2.1.2.dist-info/METADATA
nameflux-2.1.2.dist-info/WHEEL
nameflux-2.1.2.dist-info/entry_points.txt
nameflux-2.1.2.dist-info/RECORD
