Metadata-Version: 2.3
Name: nameflux
Version: 2.1.2
Summary: Renames files in powerful ways
License: MIT
Author: Steve Scholnick
Author-email: scholnicks@gmail.com
Requires-Python: >=3.13
Classifier: License :: OSI Approved :: MIT License
Classifier: Programming Language :: Python :: 3
Classifier: Programming Language :: Python :: 3.13
Requires-Dist: docopt-ng (>=0.9.0,<0.10.0)
Project-URL: Repository, https://github.com/scholnicks/nameflux
